{
  "team": "Vasas Akadémia",
  "season": "x2526",
  "count": 31,
  "matches": [
    {
      "gamecode": "hun2a_123459",
      "comp_code": "hun2a",
      "phase": "alapszakasz",
      "round": "1. forduló",
      "date": "2025-09-28",
      "time": "17:00",
      "home": false,
      "opponent": "Jászberényi KSE",
      "our_score": 82,
      "their_score": 91,
      "result": "L",
      "quarter_scores": [
        {
          "our": 25,
          "their": 31
        },
        {
          "our": 13,
          "their": 20
        },
        {
          "our": 21,
          "their": 20
        },
        {
          "our": 23,
          "their": 20
        }
      ],
      "has_scoresheet": false,
      "has_pbp": true
    },
    {
      "gamecode": "hun2a_123471",
      "comp_code": "hun2a",
      "phase": "alapszakasz",
      "round": "2. forduló",
      "date": "2025-10-04",
      "time": "18:30",
      "home": true,
      "opponent": "SALGÓTARJÁNI KSE",
      "our_score": 90,
      "their_score": 93,
      "result": "L",
      "quarter_scores": [
        {
          "our": 19,
          "their": 20
        },
        {
          "our": 27,
          "their": 17
        },
        {
          "our": 14,
          "their": 27
        },
        {
          "our": 20,
          "their": 16
        },
        {
          "our": 10,
          "their": 13
        }
      ],
      "has_scoresheet": true,
      "has_pbp": true
    },
    {
      "gamecode": "hun2a_123483",
      "comp_code": "hun2a",
      "phase": "alapszakasz",
      "round": "3. forduló",
      "date": "2025-10-10",
      "time": "18:00",
      "home": false,
      "opponent": "PVSK-Veolia",
      "our_score": 76,
      "their_score": 77,
      "result": "L",
      "quarter_scores": [
        {
          "our": 20,
          "their": 17
        },
        {
          "our": 21,
          "their": 23
        },
        {
          "our": 21,
          "their": 21
        },
        {
          "our": 14,
          "their": 16
        }
      ],
      "has_scoresheet": false,
      "has_pbp": true
    },
    {
      "gamecode": "hun2a_123495",
      "comp_code": "hun2a",
      "phase": "alapszakasz",
      "round": "4. forduló",
      "date": "2025-10-18",
      "time": "18:30",
      "home": true,
      "opponent": "HÜBNER NYÍREGYHÁZA BS",
      "our_score": 73,
      "their_score": 85,
      "result": "L",
      "quarter_scores": [
        {
          "our": 22,
          "their": 20
        },
        {
          "our": 17,
          "their": 22
        },
        {
          "our": 17,
          "their": 26
        },
        {
          "our": 17,
          "their": 17
        }
      ],
      "has_scoresheet": true,
      "has_pbp": true
    },
    {
      "gamecode": "hun2a_123507",
      "comp_code": "hun2a",
      "phase": "alapszakasz",
      "round": "5. forduló",
      "date": "2025-10-26",
      "time": "17:00",
      "home": false,
      "opponent": "BKG PRIMA AKADÉMIA",
      "our_score": 77,
      "their_score": 69,
      "result": "W",
      "quarter_scores": [
        {
          "our": 25,
          "their": 9
        },
        {
          "our": 17,
          "their": 19
        },
        {
          "our": 17,
          "their": 17
        },
        {
          "our": 18,
          "their": 24
        }
      ],
      "has_scoresheet": true,
      "has_pbp": true
    },
    {
      "gamecode": "hun2a_123519",
      "comp_code": "hun2a",
      "phase": "alapszakasz",
      "round": "6. forduló",
      "date": "2025-10-31",
      "time": "18:30",
      "home": true,
      "opponent": "PEKA BAU-MEAFC WOLVES",
      "our_score": 85,
      "their_score": 84,
      "result": "W",
      "quarter_scores": [
        {
          "our": 21,
          "their": 26
        },
        {
          "our": 24,
          "their": 16
        },
        {
          "our": 26,
          "their": 19
        },
        {
          "our": 14,
          "their": 23
        }
      ],
      "has_scoresheet": true,
      "has_pbp": true
    },
    {
      "gamecode": "hun2a_123531",
      "comp_code": "hun2a",
      "phase": "alapszakasz",
      "round": "7. forduló",
      "date": "2025-11-08",
      "time": "18:30",
      "home": true,
      "opponent": "TISZAÚJVÁROSI TERMÁLFÜRDŐ PH",
      "our_score": 91,
      "their_score": 71,
      "result": "W",
      "quarter_scores": [
        {
          "our": 25,
          "their": 22
        },
        {
          "our": 22,
          "their": 14
        },
        {
          "our": 18,
          "their": 12
        },
        {
          "our": 26,
          "their": 23
        }
      ],
      "has_scoresheet": true,
      "has_pbp": true
    },
    {
      "gamecode": "hun2a_123547",
      "comp_code": "hun2a",
      "phase": "alapszakasz",
      "round": "8. forduló",
      "date": "2025-11-17",
      "time": "17:00",
      "home": false,
      "opponent": "Phoenix-MT Fót",
      "our_score": 87,
      "their_score": 76,
      "result": "W",
      "quarter_scores": [
        {
          "our": 18,
          "their": 22
        },
        {
          "our": 30,
          "their": 16
        },
        {
          "our": 24,
          "their": 21
        },
        {
          "our": 15,
          "their": 17
        }
      ],
      "has_scoresheet": false,
      "has_pbp": true
    },
    {
      "gamecode": "hun2a_123563",
      "comp_code": "hun2a",
      "phase": "alapszakasz",
      "round": "9. forduló",
      "date": "2025-11-21",
      "time": "18:30",
      "home": true,
      "opponent": "ÚJBUDA MAFC",
      "our_score": 75,
      "their_score": 89,
      "result": "L",
      "quarter_scores": [
        {
          "our": 20,
          "their": 29
        },
        {
          "our": 21,
          "their": 21
        },
        {
          "our": 15,
          "their": 18
        },
        {
          "our": 19,
          "their": 21
        }
      ],
      "has_scoresheet": true,
      "has_pbp": true
    },
    {
      "gamecode": "hun2a_123579",
      "comp_code": "hun2a",
      "phase": "alapszakasz",
      "round": "10. forduló",
      "date": "2025-11-26",
      "time": "16:00",
      "home": false,
      "opponent": "TF-BP",
      "our_score": 89,
      "their_score": 72,
      "result": "W",
      "quarter_scores": [
        {
          "our": 31,
          "their": 16
        },
        {
          "our": 18,
          "their": 22
        },
        {
          "our": 20,
          "their": 15
        },
        {
          "our": 20,
          "their": 19
        }
      ],
      "has_scoresheet": true,
      "has_pbp": true
    },
    {
      "gamecode": "hun2a_123595",
      "comp_code": "hun2a",
      "phase": "alapszakasz",
      "round": "11. forduló",
      "date": "2025-12-05",
      "time": "18:30",
      "home": true,
      "opponent": "ÓBUDAI KASZÁSOK",
      "our_score": 78,
      "their_score": 77,
      "result": "W",
      "quarter_scores": [
        {
          "our": 15,
          "their": 24
        },
        {
          "our": 27,
          "their": 29
        },
        {
          "our": 12,
          "their": 12
        },
        {
          "our": 24,
          "their": 12
        }
      ],
      "has_scoresheet": true,
      "has_pbp": true
    },
    {
      "gamecode": "hun2a_123611",
      "comp_code": "hun2a",
      "phase": "alapszakasz",
      "round": "12. forduló",
      "date": "2025-12-14",
      "time": "18:00",
      "home": false,
      "opponent": "INSEDO VESZPRÉM KOSÁRLABDA KLUB",
      "our_score": 57,
      "their_score": 71,
      "result": "L",
      "quarter_scores": [
        {
          "our": 16,
          "their": 21
        },
        {
          "our": 19,
          "their": 15
        },
        {
          "our": 13,
          "their": 16
        },
        {
          "our": 9,
          "their": 19
        }
      ],
      "has_scoresheet": true,
      "has_pbp": true
    },
    {
      "gamecode": "hun2a_123627",
      "comp_code": "hun2a",
      "phase": "alapszakasz",
      "round": "13. forduló",
      "date": "2025-12-19",
      "time": "17:30",
      "home": true,
      "opponent": "DEAC U23",
      "our_score": 88,
      "their_score": 91,
      "result": "L",
      "quarter_scores": [
        {
          "our": 15,
          "their": 17
        },
        {
          "our": 15,
          "their": 27
        },
        {
          "our": 28,
          "their": 23
        },
        {
          "our": 30,
          "their": 24
        }
      ],
      "has_scoresheet": true,
      "has_pbp": true
    },
    {
      "gamecode": "hun2a_123641",
      "comp_code": "hun2a",
      "phase": "alapszakasz",
      "round": "14. forduló",
      "date": "2026-01-03",
      "time": "18:30",
      "home": true,
      "opponent": "JÁSZBERÉNYI KSE",
      "our_score": 94,
      "their_score": 89,
      "result": "W",
      "quarter_scores": [
        {
          "our": 15,
          "their": 19
        },
        {
          "our": 23,
          "their": 16
        },
        {
          "our": 16,
          "their": 19
        },
        {
          "our": 17,
          "their": 17
        },
        {
          "our": 8,
          "their": 8
        },
        {
          "our": 15,
          "their": 10
        }
      ],
      "has_scoresheet": true,
      "has_pbp": true
    },
    {
      "gamecode": "hun2a_123653",
      "comp_code": "hun2a",
      "phase": "alapszakasz",
      "round": "15. forduló",
      "date": "2026-01-09",
      "time": "17:00",
      "home": false,
      "opponent": "EBH-SALGÓTARJÁN",
      "our_score": 59,
      "their_score": 82,
      "result": "L",
      "quarter_scores": [
        {
          "our": 9,
          "their": 22
        },
        {
          "our": 18,
          "their": 22
        },
        {
          "our": 19,
          "their": 21
        },
        {
          "our": 13,
          "their": 17
        }
      ],
      "has_scoresheet": true,
      "has_pbp": true
    },
    {
      "gamecode": "hun2a_123665",
      "comp_code": "hun2a",
      "phase": "alapszakasz",
      "round": "16. forduló",
      "date": "2026-01-17",
      "time": "18:30",
      "home": true,
      "opponent": "PVSK-VEOLIA",
      "our_score": 76,
      "their_score": 86,
      "result": "L",
      "quarter_scores": [
        {
          "our": 25,
          "their": 22
        },
        {
          "our": 23,
          "their": 24
        },
        {
          "our": 10,
          "their": 21
        },
        {
          "our": 18,
          "their": 19
        }
      ],
      "has_scoresheet": true,
      "has_pbp": true
    },
    {
      "gamecode": "hun2a_123677",
      "comp_code": "hun2a",
      "phase": "alapszakasz",
      "round": "17. forduló",
      "date": "2026-01-25",
      "time": "17:00",
      "home": false,
      "opponent": "HÜBNER NYÍREGYHÁZA BS",
      "our_score": 75,
      "their_score": 69,
      "result": "W",
      "quarter_scores": [
        {
          "our": 12,
          "their": 16
        },
        {
          "our": 17,
          "their": 22
        },
        {
          "our": 22,
          "their": 13
        },
        {
          "our": 13,
          "their": 13
        },
        {
          "our": 11,
          "their": 5
        }
      ],
      "has_scoresheet": true,
      "has_pbp": true
    },
    {
      "gamecode": "hun2a_123689",
      "comp_code": "hun2a",
      "phase": "alapszakasz",
      "round": "18. forduló",
      "date": "2026-01-31",
      "time": "18:30",
      "home": true,
      "opponent": "BKG PRIMA AKADÉMIA",
      "our_score": 77,
      "their_score": 80,
      "result": "L",
      "quarter_scores": [
        {
          "our": 17,
          "their": 16
        },
        {
          "our": 23,
          "their": 27
        },
        {
          "our": 18,
          "their": 18
        },
        {
          "our": 19,
          "their": 19
        }
      ],
      "has_scoresheet": true,
      "has_pbp": true
    },
    {
      "gamecode": "hun2a_123701",
      "comp_code": "hun2a",
      "phase": "alapszakasz",
      "round": "19. forduló",
      "date": "2026-02-07",
      "time": "17:00",
      "home": false,
      "opponent": "PEKA BAU-MEAFC WOLVES",
      "our_score": 79,
      "their_score": 88,
      "result": "L",
      "quarter_scores": [
        {
          "our": 23,
          "their": 26
        },
        {
          "our": 14,
          "their": 20
        },
        {
          "our": 27,
          "their": 20
        },
        {
          "our": 15,
          "their": 22
        }
      ],
      "has_scoresheet": true,
      "has_pbp": true
    },
    {
      "gamecode": "hun2a_123713",
      "comp_code": "hun2a",
      "phase": "alapszakasz",
      "round": "20. forduló",
      "date": "2026-02-13",
      "time": "18:00",
      "home": false,
      "opponent": "TISZAÚJVÁROSI TERMÁLFÜRDŐ PHOENIX KK",
      "our_score": 63,
      "their_score": 71,
      "result": "L",
      "quarter_scores": [
        {
          "our": 19,
          "their": 21
        },
        {
          "our": 13,
          "their": 15
        },
        {
          "our": 9,
          "their": 12
        },
        {
          "our": 22,
          "their": 23
        }
      ],
      "has_scoresheet": true,
      "has_pbp": true
    },
    {
      "gamecode": "hun2a_123729",
      "comp_code": "hun2a",
      "phase": "alapszakasz",
      "round": "21. forduló",
      "date": "2026-02-19",
      "time": "17:00",
      "home": true,
      "opponent": "PHOENIX-MT FÓT",
      "our_score": 73,
      "their_score": 87,
      "result": "L",
      "quarter_scores": [
        {
          "our": 23,
          "their": 22
        },
        {
          "our": 18,
          "their": 25
        },
        {
          "our": 15,
          "their": 21
        },
        {
          "our": 17,
          "their": 19
        }
      ],
      "has_scoresheet": true,
      "has_pbp": true
    },
    {
      "gamecode": "hun2a_123745",
      "comp_code": "hun2a",
      "phase": "alapszakasz",
      "round": "22. forduló",
      "date": "2026-03-07",
      "time": "17:30",
      "home": false,
      "opponent": "ÚJBUDA MAFC",
      "our_score": 70,
      "their_score": 78,
      "result": "L",
      "quarter_scores": [
        {
          "our": 25,
          "their": 23
        },
        {
          "our": 19,
          "their": 18
        },
        {
          "our": 14,
          "their": 18
        },
        {
          "our": 12,
          "their": 19
        }
      ],
      "has_scoresheet": true,
      "has_pbp": true
    },
    {
      "gamecode": "hun2a_123761",
      "comp_code": "hun2a",
      "phase": "alapszakasz",
      "round": "23. forduló",
      "date": "2026-03-14",
      "time": "18:30",
      "home": true,
      "opponent": "TF-BP",
      "our_score": 89,
      "their_score": 70,
      "result": "W",
      "quarter_scores": [
        {
          "our": 26,
          "their": 13
        },
        {
          "our": 26,
          "their": 26
        },
        {
          "our": 12,
          "their": 20
        },
        {
          "our": 25,
          "their": 11
        }
      ],
      "has_scoresheet": true,
      "has_pbp": true
    },
    {
      "gamecode": "hun2a_123777",
      "comp_code": "hun2a",
      "phase": "alapszakasz",
      "round": "24. forduló",
      "date": "2026-03-21",
      "time": "16:45",
      "home": false,
      "opponent": "ÓBUDAI KASZÁSOK",
      "our_score": 73,
      "their_score": 77,
      "result": "L",
      "quarter_scores": [
        {
          "our": 16,
          "their": 21
        },
        {
          "our": 20,
          "their": 19
        },
        {
          "our": 18,
          "their": 21
        },
        {
          "our": 19,
          "their": 16
        }
      ],
      "has_scoresheet": true,
      "has_pbp": true
    },
    {
      "gamecode": "hun2a_123793",
      "comp_code": "hun2a",
      "phase": "alapszakasz",
      "round": "25. forduló",
      "date": "2026-03-28",
      "time": "18:30",
      "home": true,
      "opponent": "INSEDO VESZPRÉM KOSÁRLABDA K",
      "our_score": 69,
      "their_score": 96,
      "result": "L",
      "quarter_scores": [
        {
          "our": 16,
          "their": 27
        },
        {
          "our": 12,
          "their": 23
        },
        {
          "our": 16,
          "their": 21
        },
        {
          "our": 25,
          "their": 25
        }
      ],
      "has_scoresheet": true,
      "has_pbp": true
    },
    {
      "gamecode": "hun2a_123809",
      "comp_code": "hun2a",
      "phase": "alapszakasz",
      "round": "26. forduló",
      "date": "2026-04-05",
      "time": "18:00",
      "home": false,
      "opponent": "DEAC U23",
      "our_score": 61,
      "their_score": 55,
      "result": "W",
      "quarter_scores": [
        {
          "our": 14,
          "their": 19
        },
        {
          "our": 16,
          "their": 18
        },
        {
          "our": 16,
          "their": 9
        },
        {
          "our": 15,
          "their": 9
        }
      ],
      "has_scoresheet": false,
      "has_pbp": true
    },
    {
      "gamecode": "hun2a_plya_134145",
      "comp_code": "hun2a_plya",
      "phase": "rajatszas_also",
      "round": "1. forduló",
      "date": "2026-04-14",
      "time": "18:00",
      "home": true,
      "opponent": "TF-BP",
      "our_score": 73,
      "their_score": 65,
      "result": "W",
      "quarter_scores": [
        {
          "our": 19,
          "their": 14
        },
        {
          "our": 20,
          "their": 16
        },
        {
          "our": 16,
          "their": 24
        },
        {
          "our": 18,
          "their": 11
        }
      ],
      "has_scoresheet": true,
      "has_pbp": true
    },
    {
      "gamecode": "hun2a_plya_134147",
      "comp_code": "hun2a_plya",
      "phase": "rajatszas_also",
      "round": "1. forduló",
      "date": "2026-04-17",
      "time": "19:00",
      "home": false,
      "opponent": "TF-BP",
      "our_score": 71,
      "their_score": 61,
      "result": "W",
      "quarter_scores": [
        {
          "our": 23,
          "their": 11
        },
        {
          "our": 19,
          "their": 17
        },
        {
          "our": 18,
          "their": 15
        },
        {
          "our": 11,
          "their": 18
        }
      ],
      "has_scoresheet": true,
      "has_pbp": true
    },
    {
      "gamecode": "hun2a_plya_134163",
      "comp_code": "hun2a_plya",
      "phase": "rajatszas_also",
      "round": "2. forduló",
      "date": "2026-04-30",
      "time": "19:00",
      "home": false,
      "opponent": "Jászberényi KSE",
      "our_score": null,
      "their_score": null,
      "result": null,
      "quarter_scores": null,
      "has_scoresheet": false,
      "has_pbp": true
    },
    {
      "gamecode": "hun2a_plya_134165",
      "comp_code": "hun2a_plya",
      "phase": "rajatszas_also",
      "round": "2. forduló",
      "date": "2026-05-03",
      "time": "17:00",
      "home": true,
      "opponent": "Jászberényi KSE",
      "our_score": null,
      "their_score": null,
      "result": null,
      "quarter_scores": null,
      "has_scoresheet": false,
      "has_pbp": true
    },
    {
      "gamecode": "hun2a_plya_134167",
      "comp_code": "hun2a_plya",
      "phase": "rajatszas_also",
      "round": "2. forduló",
      "date": "2026-05-06",
      "time": "18:00",
      "home": false,
      "opponent": "Jászberényi KSE",
      "our_score": null,
      "their_score": null,
      "result": null,
      "quarter_scores": null,
      "has_scoresheet": false,
      "has_pbp": true
    }
  ]
}
