{
  "team": "Óbudai Kaszások",
  "season": "x2526",
  "team_max_gp": 28,
  "thresholds": {
    "min_gp_for_percentile": 5,
    "min_fga": 50,
    "min_3pa": 15,
    "min_fta": 10
  },
  "players": [
    {
      "name": "Swanson Kevin Wade",
      "jersey": 33,
      "gp": 28,
      "starts": 28,
      "gs_rate": 1.0,
      "mpg": 31.4,
      "ppg": 20.2,
      "rpg": 8.0,
      "oreb_pg": 2.8,
      "dreb_pg": 5.2,
      "apg": 1.5,
      "tpg": 2.6,
      "spg": 0.9,
      "bpg": 0.5,
      "fpg": 2.2,
      "fdpg": 4.1,
      "ato": 0.55,
      "fg_made": 220,
      "fg_att": 439,
      "fg_pct": 50.1,
      "three_made": 39,
      "three_att": 130,
      "three_pct": 30.0,
      "ft_made": 88,
      "ft_att": 141,
      "ft_pct": 62.4,
      "photo_filename": "obudai-kaszasok-swanson-kevin-wade.jpg",
      "height_cm": 201,
      "position": "4",
      "birth_year": 1993,
      "percentiles": {
        "ppg": 96,
        "rpg": 94,
        "oreb_pg": 98,
        "dreb_pg": 93,
        "apg": 67,
        "spg": 74,
        "bpg": 93,
        "fdpg": 90,
        "mpg": 90,
        "tpg": 95,
        "fpg": 72,
        "fg_pct": 79,
        "three_pct": 46,
        "ft_pct": 32
      }
    },
    {
      "name": "Homoki Donát László",
      "jersey": 14,
      "gp": 27,
      "starts": 27,
      "gs_rate": 1.0,
      "mpg": 27.2,
      "ppg": 17.2,
      "rpg": 9.8,
      "oreb_pg": 2.1,
      "dreb_pg": 7.7,
      "apg": 0.9,
      "tpg": 1.8,
      "spg": 0.6,
      "bpg": 0.2,
      "fpg": 3.1,
      "fdpg": 3.0,
      "ato": 0.47,
      "fg_made": 175,
      "fg_att": 374,
      "fg_pct": 46.8,
      "three_made": 43,
      "three_att": 147,
      "three_pct": 29.3,
      "ft_made": 72,
      "ft_att": 102,
      "ft_pct": 70.6,
      "photo_filename": "obudai-kaszasok-homoki-donat-laszlo.jpg",
      "height_cm": 205,
      "position": "4-5",
      "birth_year": 1998,
      "percentiles": {
        "ppg": 91,
        "rpg": 99,
        "oreb_pg": 94,
        "dreb_pg": 100,
        "apg": 50,
        "spg": 57,
        "bpg": 78,
        "fdpg": 78,
        "mpg": 79,
        "tpg": 83,
        "fpg": 98,
        "fg_pct": 67,
        "three_pct": 40,
        "ft_pct": 55
      }
    },
    {
      "name": "Boros Márk",
      "jersey": 13,
      "gp": 27,
      "starts": 26,
      "gs_rate": 0.963,
      "mpg": 24.9,
      "ppg": 11.4,
      "rpg": 3.2,
      "oreb_pg": 0.5,
      "dreb_pg": 2.7,
      "apg": 5.3,
      "tpg": 2.5,
      "spg": 1.1,
      "bpg": 0.1,
      "fpg": 1.4,
      "fdpg": 3.6,
      "ato": 2.13,
      "fg_made": 107,
      "fg_att": 294,
      "fg_pct": 36.4,
      "three_made": 24,
      "three_att": 100,
      "three_pct": 24.0,
      "ft_made": 71,
      "ft_att": 105,
      "ft_pct": 67.6,
      "photo_filename": "obudai-kaszasok-boros-mark.jpg",
      "height_cm": 188,
      "position": "1-3",
      "birth_year": 1997,
      "percentiles": {
        "ppg": 79,
        "rpg": 62,
        "oreb_pg": 50,
        "dreb_pg": 67,
        "apg": 97,
        "spg": 85,
        "bpg": 63,
        "fdpg": 86,
        "mpg": 75,
        "tpg": 92,
        "fpg": 38,
        "fg_pct": 13,
        "three_pct": 18,
        "ft_pct": 45
      }
    },
    {
      "name": "Balázsi Ákos Milán",
      "jersey": 10,
      "gp": 11,
      "starts": 8,
      "gs_rate": 0.727,
      "mpg": 28.8,
      "ppg": 13.0,
      "rpg": 5.0,
      "oreb_pg": 1.9,
      "dreb_pg": 3.1,
      "apg": 1.9,
      "tpg": 1.0,
      "spg": 1.4,
      "bpg": 0.0,
      "fpg": 2.2,
      "fdpg": 2.5,
      "ato": 1.91,
      "fg_made": 56,
      "fg_att": 79,
      "fg_pct": 70.9,
      "three_made": 14,
      "three_att": 29,
      "three_pct": 48.3,
      "ft_made": 17,
      "ft_att": 24,
      "ft_pct": 70.8,
      "photo_filename": "obudai-kaszasok-balazsi-akos-milan.jpg",
      "height_cm": 193,
      "position": "2",
      "birth_year": 2005,
      "percentiles": {
        "ppg": 83,
        "rpg": 84,
        "oreb_pg": 90,
        "dreb_pg": 77,
        "apg": 73,
        "spg": 89,
        "bpg": 40,
        "fdpg": 76,
        "mpg": 85,
        "tpg": 53,
        "fpg": 72,
        "fg_pct": 100,
        "three_pct": 99,
        "ft_pct": 58
      }
    },
    {
      "name": "Balázsi Bence Soma",
      "jersey": 9,
      "gp": 27,
      "starts": 16,
      "gs_rate": 0.593,
      "mpg": 17.1,
      "ppg": 2.5,
      "rpg": 2.6,
      "oreb_pg": 0.9,
      "dreb_pg": 1.7,
      "apg": 1.2,
      "tpg": 0.6,
      "spg": 0.6,
      "bpg": 0.1,
      "fpg": 3.0,
      "fdpg": 0.6,
      "ato": 1.88,
      "fg_made": 26,
      "fg_att": 57,
      "fg_pct": 45.6,
      "three_made": 11,
      "three_att": 35,
      "three_pct": 31.4,
      "ft_made": 4,
      "ft_att": 7,
      "ft_pct": 57.1,
      "photo_filename": "obudai-kaszasok-balazsi-bence-soma.jpg",
      "height_cm": 194,
      "position": "3-4",
      "birth_year": 2001,
      "percentiles": {
        "ppg": 32,
        "rpg": 51,
        "oreb_pg": 66,
        "dreb_pg": 50,
        "apg": 59,
        "spg": 57,
        "bpg": 63,
        "fdpg": 35,
        "mpg": 52,
        "tpg": 38,
        "fpg": 96,
        "fg_pct": 57,
        "three_pct": 55
      }
    },
    {
      "name": "Hajdu Gergely",
      "jersey": 19,
      "gp": 22,
      "starts": 13,
      "gs_rate": 0.591,
      "mpg": 15.2,
      "ppg": 2.5,
      "rpg": 1.8,
      "oreb_pg": 0.7,
      "dreb_pg": 1.1,
      "apg": 0.9,
      "tpg": 1.2,
      "spg": 0.6,
      "bpg": 0.0,
      "fpg": 1.8,
      "fdpg": 0.7,
      "ato": 0.74,
      "fg_made": 19,
      "fg_att": 82,
      "fg_pct": 23.2,
      "three_made": 11,
      "three_att": 65,
      "three_pct": 16.9,
      "ft_made": 5,
      "ft_att": 8,
      "ft_pct": 62.5,
      "photo_filename": "obudai-kaszasok-hajdu-gergely.jpg",
      "height_cm": 190,
      "position": "1-3",
      "birth_year": 2005,
      "percentiles": {
        "ppg": 32,
        "rpg": 40,
        "oreb_pg": 60,
        "dreb_pg": 38,
        "apg": 50,
        "spg": 57,
        "bpg": 40,
        "fdpg": 38,
        "mpg": 44,
        "tpg": 64,
        "fpg": 48,
        "fg_pct": 2,
        "three_pct": 9
      }
    },
    {
      "name": "Horvat Olivér Márk",
      "jersey": 25,
      "gp": 9,
      "starts": 5,
      "gs_rate": 0.556,
      "mpg": 11.9,
      "ppg": 1.7,
      "rpg": 0.8,
      "oreb_pg": 0.4,
      "dreb_pg": 0.3,
      "apg": 1.2,
      "tpg": 0.4,
      "spg": 1.0,
      "bpg": 0.0,
      "fpg": 2.2,
      "fdpg": 0.3,
      "ato": 2.75,
      "fg_made": 6,
      "fg_att": 11,
      "fg_pct": 54.5,
      "three_made": 2,
      "three_att": 6,
      "three_pct": 33.3,
      "ft_made": 1,
      "ft_att": 1,
      "ft_pct": 100.0,
      "percentiles": {
        "ppg": 25,
        "rpg": 24,
        "oreb_pg": 41,
        "dreb_pg": 19,
        "apg": 59,
        "spg": 79,
        "bpg": 40,
        "fdpg": 26,
        "mpg": 36,
        "tpg": 30,
        "fpg": 72
      }
    },
    {
      "name": "Horváth Botond",
      "jersey": 3,
      "gp": 23,
      "starts": 12,
      "gs_rate": 0.522,
      "mpg": 16.8,
      "ppg": 5.6,
      "rpg": 1.0,
      "oreb_pg": 0.3,
      "dreb_pg": 0.7,
      "apg": 1.3,
      "tpg": 0.6,
      "spg": 0.6,
      "bpg": 0.1,
      "fpg": 2.1,
      "fdpg": 0.8,
      "ato": 2.23,
      "fg_made": 43,
      "fg_att": 101,
      "fg_pct": 42.6,
      "three_made": 21,
      "three_att": 64,
      "three_pct": 32.8,
      "ft_made": 21,
      "ft_att": 23,
      "ft_pct": 91.3,
      "photo_filename": "obudai-kaszasok-horvath-botond.jpg",
      "height_cm": 190,
      "position": "1-3",
      "birth_year": 2003,
      "percentiles": {
        "ppg": 50,
        "rpg": 28,
        "oreb_pg": 32,
        "dreb_pg": 30,
        "apg": 64,
        "spg": 57,
        "bpg": 63,
        "fdpg": 41,
        "mpg": 50,
        "tpg": 38,
        "fpg": 64,
        "fg_pct": 44,
        "three_pct": 64,
        "ft_pct": 100
      }
    },
    {
      "name": "Gazdag Áron Bendegúz",
      "jersey": 22,
      "gp": 26,
      "starts": 2,
      "gs_rate": 0.077,
      "mpg": 14.2,
      "ppg": 3.9,
      "rpg": 3.0,
      "oreb_pg": 0.8,
      "dreb_pg": 2.2,
      "apg": 0.3,
      "tpg": 0.7,
      "spg": 0.3,
      "bpg": 0.5,
      "fpg": 1.5,
      "fdpg": 0.4,
      "ato": 0.44,
      "fg_made": 45,
      "fg_att": 92,
      "fg_pct": 48.9,
      "three_made": 1,
      "three_att": 10,
      "three_pct": 10.0,
      "ft_made": 10,
      "ft_att": 14,
      "ft_pct": 71.4,
      "photo_filename": "obudai-kaszasok-gazdag-aron-bendeguz.jpg",
      "height_cm": 207,
      "position": "5",
      "birth_year": 2005,
      "percentiles": {
        "ppg": 40,
        "rpg": 58,
        "oreb_pg": 64,
        "dreb_pg": 60,
        "apg": 33,
        "spg": 34,
        "bpg": 93,
        "fdpg": 31,
        "mpg": 39,
        "tpg": 44,
        "fpg": 40,
        "fg_pct": 76,
        "ft_pct": 61
      }
    },
    {
      "name": "Szántó Dániel",
      "jersey": 8,
      "gp": 28,
      "starts": 2,
      "gs_rate": 0.071,
      "mpg": 16.8,
      "ppg": 4.7,
      "rpg": 2.9,
      "oreb_pg": 0.6,
      "dreb_pg": 2.3,
      "apg": 3.7,
      "tpg": 2.1,
      "spg": 1.2,
      "bpg": 0.2,
      "fpg": 2.1,
      "fdpg": 2.6,
      "ato": 1.79,
      "fg_made": 38,
      "fg_att": 83,
      "fg_pct": 45.8,
      "three_made": 3,
      "three_att": 15,
      "three_pct": 20.0,
      "ft_made": 52,
      "ft_att": 74,
      "ft_pct": 70.3,
      "photo_filename": "obudai-kaszasok-szanto-daniel.jpg",
      "height_cm": 188,
      "position": "1-2",
      "birth_year": 2000,
      "percentiles": {
        "ppg": 44,
        "rpg": 55,
        "oreb_pg": 55,
        "dreb_pg": 61,
        "apg": 88,
        "spg": 87,
        "bpg": 78,
        "fdpg": 76,
        "mpg": 50,
        "tpg": 88,
        "fpg": 64,
        "fg_pct": 62,
        "three_pct": 11,
        "ft_pct": 53
      }
    },
    {
      "name": "Lakosa Ákos",
      "jersey": 17,
      "gp": 27,
      "starts": 1,
      "gs_rate": 0.037,
      "mpg": 18.0,
      "ppg": 8.1,
      "rpg": 2.7,
      "oreb_pg": 0.7,
      "dreb_pg": 2.0,
      "apg": 2.1,
      "tpg": 1.5,
      "spg": 1.1,
      "bpg": 0.1,
      "fpg": 1.7,
      "fdpg": 2.3,
      "ato": 1.37,
      "fg_made": 74,
      "fg_att": 183,
      "fg_pct": 40.4,
      "three_made": 34,
      "three_att": 100,
      "three_pct": 34.0,
      "ft_made": 37,
      "ft_att": 61,
      "ft_pct": 60.7,
      "photo_filename": "obudai-kaszasok-lakosa-akos.jpg",
      "height_cm": 188,
      "position": "1-2",
      "birth_year": 1992,
      "percentiles": {
        "ppg": 62,
        "rpg": 52,
        "oreb_pg": 60,
        "dreb_pg": 56,
        "apg": 76,
        "spg": 85,
        "bpg": 63,
        "fdpg": 73,
        "mpg": 54,
        "tpg": 77,
        "fpg": 46,
        "fg_pct": 34,
        "three_pct": 69,
        "ft_pct": 26
      }
    },
    {
      "name": "Varsányi Áron",
      "jersey": 2,
      "gp": 27,
      "starts": 0,
      "gs_rate": 0.0,
      "mpg": 6.4,
      "ppg": 1.9,
      "rpg": 0.9,
      "oreb_pg": 0.3,
      "dreb_pg": 0.6,
      "apg": 0.3,
      "tpg": 0.4,
      "spg": 0.1,
      "bpg": 0.0,
      "fpg": 0.7,
      "fdpg": 0.4,
      "ato": 0.64,
      "fg_made": 18,
      "fg_att": 61,
      "fg_pct": 29.5,
      "three_made": 10,
      "three_att": 41,
      "three_pct": 24.4,
      "ft_made": 6,
      "ft_att": 10,
      "ft_pct": 60.0,
      "photo_filename": "obudai-kaszasok-varsanyi-aron.jpg",
      "height_cm": 181,
      "position": "1-2",
      "birth_year": 2004,
      "percentiles": {
        "ppg": 27,
        "rpg": 26,
        "oreb_pg": 32,
        "dreb_pg": 28,
        "apg": 33,
        "spg": 21,
        "bpg": 40,
        "fdpg": 31,
        "mpg": 25,
        "tpg": 30,
        "fpg": 22,
        "fg_pct": 5,
        "three_pct": 22,
        "ft_pct": 25
      }
    },
    {
      "name": "Patai Dániel András",
      "jersey": 11,
      "gp": 3,
      "starts": 0,
      "gs_rate": 0.0,
      "mpg": 5.7,
      "ppg": 0.0,
      "rpg": 0.3,
      "oreb_pg": 0.0,
      "dreb_pg": 0.3,
      "apg": 0.3,
      "tpg": 0.3,
      "spg": 0.0,
      "bpg": 0.0,
      "fpg": 1.0,
      "fdpg": 0.0,
      "ato": 1.0,
      "fg_made": 0,
      "fg_att": 3,
      "fg_pct": 0.0,
      "three_made": 0,
      "three_att": 3,
      "three_pct": 0.0,
      "ft_made": 0,
      "ft_att": 0,
      "ft_pct": null,
      "photo_filename": "obudai-kaszasok-patai-daniel-andras.jpg",
      "height_cm": 183,
      "position": "1-2",
      "birth_year": 2006,
      "percentiles": {}
    },
    {
      "name": "Nshimba Kalau Joel",
      "jersey": 6,
      "gp": 26,
      "starts": 0,
      "gs_rate": 0.0,
      "mpg": 5.2,
      "ppg": 2.0,
      "rpg": 1.6,
      "oreb_pg": 0.5,
      "dreb_pg": 1.1,
      "apg": 0.0,
      "tpg": 0.5,
      "spg": 0.1,
      "bpg": 0.1,
      "fpg": 1.4,
      "fdpg": 0.5,
      "ato": 0.07,
      "fg_made": 20,
      "fg_att": 43,
      "fg_pct": 46.5,
      "three_made": 3,
      "three_att": 12,
      "three_pct": 25.0,
      "ft_made": 9,
      "ft_att": 15,
      "ft_pct": 60.0,
      "photo_filename": "obudai-kaszasok-nshimba-kalau-joel.jpg",
      "height_cm": 200,
      "position": "4-5",
      "birth_year": 1998,
      "percentiles": {
        "ppg": 28,
        "rpg": 37,
        "oreb_pg": 50,
        "dreb_pg": 38,
        "apg": 11,
        "spg": 21,
        "bpg": 63,
        "fdpg": 33,
        "mpg": 23,
        "tpg": 34,
        "fpg": 38,
        "ft_pct": 25
      }
    },
    {
      "name": "Szabó Dániel",
      "jersey": 21,
      "gp": 19,
      "starts": 0,
      "gs_rate": 0.0,
      "mpg": 4.2,
      "ppg": 1.6,
      "rpg": 0.8,
      "oreb_pg": 0.1,
      "dreb_pg": 0.7,
      "apg": 0.0,
      "tpg": 0.1,
      "spg": 0.2,
      "bpg": 0.1,
      "fpg": 0.3,
      "fdpg": 0.2,
      "ato": 0.0,
      "fg_made": 8,
      "fg_att": 24,
      "fg_pct": 33.3,
      "three_made": 8,
      "three_att": 19,
      "three_pct": 42.1,
      "ft_made": 6,
      "ft_att": 8,
      "ft_pct": 75.0,
      "photo_filename": "obudai-kaszasok-szabo-daniel.jpg",
      "height_cm": 198,
      "position": "1-3",
      "birth_year": 2004,
      "percentiles": {
        "ppg": 25,
        "rpg": 24,
        "oreb_pg": 18,
        "dreb_pg": 30,
        "apg": 11,
        "spg": 31,
        "bpg": 63,
        "fdpg": 20,
        "mpg": 19,
        "tpg": 14,
        "fpg": 12,
        "three_pct": 93
      }
    },
    {
      "name": "Lehoczki Attila",
      "jersey": 26,
      "gp": 2,
      "starts": 0,
      "gs_rate": 0.0,
      "mpg": 3.0,
      "ppg": 0.0,
      "rpg": 0.5,
      "oreb_pg": 0.0,
      "dreb_pg": 0.5,
      "apg": 0.0,
      "tpg": 0.0,
      "spg": 0.0,
      "bpg": 0.0,
      "fpg": 0.0,
      "fdpg": 0.0,
      "ato": null,
      "fg_made": 0,
      "fg_att": 3,
      "fg_pct": 0.0,
      "three_made": 0,
      "three_att": 2,
      "three_pct": 0.0,
      "ft_made": 0,
      "ft_att": 0,
      "ft_pct": null,
      "photo_filename": "obudai-kaszasok-lehoczki-attila.jpg",
      "height_cm": 183,
      "position": "1-2",
      "birth_year": 2006,
      "percentiles": {}
    },
    {
      "name": "Kiss Koppány Agád",
      "jersey": 32,
      "gp": 2,
      "starts": 0,
      "gs_rate": 0.0,
      "mpg": 2.5,
      "ppg": 1.0,
      "rpg": 0.5,
      "oreb_pg": 0.5,
      "dreb_pg": 0.0,
      "apg": 0.0,
      "tpg": 0.0,
      "spg": 0.5,
      "bpg": 0.0,
      "fpg": 0.5,
      "fdpg": 0.0,
      "ato": null,
      "fg_made": 1,
      "fg_att": 1,
      "fg_pct": 100.0,
      "three_made": 0,
      "three_att": 0,
      "three_pct": null,
      "ft_made": 0,
      "ft_att": 0,
      "ft_pct": null,
      "photo_filename": "obudai-kaszasok-kiss-koppany-agad.jpg",
      "height_cm": 180,
      "position": "1-2",
      "birth_year": 2006,
      "percentiles": {}
    }
  ]
}
